pxl/__init__.py
pxl/fdiff.py
pxl/io.py
pxl/styleplot.py
pxl/timeseries.py
pxl/tests/__init__.py
pxl/tests/test_fdiff.py
pxl/tests/test_io.py
pxl/tests/test_styleplot.py
pxl/tests/test_timeseries.py
pxl-0.0.10.dist-info/METADATA
pxl-0.0.10.dist-info/WHEEL
pxl-0.0.10.dist-info/licenses/LICENSE
pxl-0.0.10.dist-info/RECORD
